Metadata-Version: 2.1
Name: veribot
Version: 1.1.0
Summary: VeriBot is a bot that can be used for verification.
Home-page: https://github.com/TheMaster3558/veribot
Author: The Master
License: MIT
Project-URL: GitHub, https://github.com/TheMaster3558/veribot
Classifier: Development Status :: 5 - Production/Stable
Classifier: License :: OSI Approved :: MIT License
Classifier: Intended Audience :: Developers
Classifier: Natural Language :: English
Classifier: Operating System :: OS Independent
Classifier: Programming Language :: Python :: 3.8
Classifier: Programming Language :: Python :: 3.9
Classifier: Programming Language :: Python :: 3.10
Classifier: Programming Language :: Python :: 3.11
Classifier: Topic :: Internet
Classifier: Topic :: Software Development :: Libraries
Classifier: Topic :: Software Development :: Libraries :: Python Modules
Classifier: Typing :: Typed
Requires-Python: >=3.7.0
License-File: LICENSE
